[
    {"id": 1, 
	 "date": "7/10", 
	 "dayOfWeek": "Tuesday",
	 "monthDate": "July 10",
	 "year": "2012", 
	 "venue": "Verizon Wireless at Encore Park",
	 "venueNoSpecialChars": "Verizon Wireless at Encore Park",
	 "altName": "Alpharetta",
	 "showTimes": "Show: 7:00pm Doors: 5:30pm EDT",
	 "capacity": "Capacity: 12,000",
	 "address1": "2200 Encore Parkway",
	 "city": "Alpharetta",
	 "state": "GA",
	 "postal": "30009",
	 "country": "USA",
	 "phone": "404-733-5010",
	 "venueURL": "http://www.vzwamp.com/",
	 "setlistURL": "http://deadheadland.com/furthur20120710",
	 "seatingURL": "http://media.ticketmaster.com/tm/en-us/tmimages/venue/maps/atl/42284s.gif",
	 "suppressMapsVenue": false,
	 "coordinates":"",
	 "tourName": "Summer 2012"		
	},
	{"id": 2, 
	 "date": "7/11", 
	 "dayOfWeek": "Wednesday", 
	 "monthDate": "July 11",
	 "year": "2012", 
	 "venue": "Koka Booth Amphitheatre",
	 "venueNoSpecialChars": "Koka Booth Amphitheatre",
	 "altName": "Koka Booth",
	 "showTimes": "Show: 6:30pm Doors: 5:00pm EDT",
	 "capacity": "Capacity: 7,000", 	
	 "address1": "8003 Regency Pkwy",
	 "city": "Cary",
	 "state": "NC",
	 "postal": "27518",
	 "country": "USA",
	 "phone": "919.462.2052",
	 "venueURL": "http://boothamphitheatre.com/",
	 "setlistURL": "http://deadheadland.com/furthur20120711",
	 "seatingURL": "http://media.ticketmaster.com/tm/en-us/tmimages/venue/maps/atl/28591s.gif",
	 "suppressMapsVenue": false,
	 "coordinates":"",
	 "tourName": "Summer 2012"		
	},
	{"id": 3, 
	 "date": "7/13", 
	 "dayOfWeek": "Friday", 
	 "monthDate": "July 13",
	 "year": "2012", 
	 "venue": "MCU Park",
	 "venueNoSpecialChars": "MCU Park",
	 "altName": "Brooklyn",
	 "showTimes": "Show: 7:00pm Doors: 5:30pm EDT",
	 "capacity": "Capacity: 6500",
	 "address1": "1904 Surf Avenue",
	 "city": "Brooklyn",
	 "state": "NY",
	 "postal": "11224",
	 "country": "USA",
	 "phone": " 718-449-8497",
	 "venueURL": "http://www.brooklyncyclones.com/",
	 "setlistURL": "http://deadheadland.com/furthur20120713",
	 "seatingURL": "http://brooklyncyclones.com.ismmedia.com/ISM3/std-content/repos/Top/Pictures/2012PRICINGMAP_RGB.jpg",
	 "suppressMapsVenue": false,
	 "coordinates":"",
	 "tourName": "Summer 2012"		
	},
	{"id": 4, 
	 "date": "7/14", 
	 "dayOfWeek": "Saturday", 
	 "monthDate": "July 14",
	 "year": "2012", 
	 "venue": "MCU Park",
	 "venueNoSpecialChars": "MCU Park",
	 "altName": "Brooklyn",
	 "showTimes": "Show: 7:00pm Doors: 5:30pm EDT",
	 "capacity": "Capacity: 6500",
	 "address1": "1904 Surf Avenue",
	 "city": "Brooklyn",
	 "state": "NY",
	 "postal": "11224",
	 "country": "USA",
	 "phone": "718-449-8497",
	 "venueURL": "http://www.brooklyncyclones.com/",
	 "setlistURL": "http://deadheadland.com/furthur20120714",
	 "seatingURL": "http://brooklyncyclones.com.ismmedia.com/ISM3/std-content/repos/Top/Pictures/2012PRICINGMAP_RGB.jpg",
	 "suppressMapsVenue": false,
	 "coordinates":"",
	 "tourName": "Summer 2012"		
	},
	{"id": 5, 
	 "date": "7/15", 
	 "dayOfWeek": "Sunday", 
	 "monthDate": "July 15",
	 "year": "2012", 
	 "venue": "Bethel Woods PAC",
	 "venueNoSpecialChars": "Bethel Woods",
	 "altName": "Bethel",
	 "showTimes": "Show: 7:00pm Doors: 5:30pm EDT",
	 "capacity": "Capacity: 15,000",
	 "address1": "200 Hurd Road",
	 "city": "Bethel",
	 "state": "NY",
	 "postal": "12720",
	 "country": "USA",
	 "phone": "1-866-781-2922",
	 "venueURL": "http://www.bethelwoodscenter.org/",
	 "setlistURL": "http://deadheadland.com/furthur20120715",
	 "seatingURL": "http://www.bethelwoodscenter.org/Portals/0/images/seatingchart.jpg",
	 "suppressMapsVenue": false,
	 "coordinates":"",
	 "tourName": "Summer 2012"		
	},
	{"id": 6, 
	 "date": "7/17", 
	 "dayOfWeek": "Tuesday", 
	 "monthDate": "July 17",
	 "year": "2012", 
	 "venue": "Charter One Pavilion",
	 "venueNoSpecialChars": "Charter One Pavilion",
	 "altName": "Chicago",
	 "showTimes": "Show: 7:00pm Doors: 5:30pm CDT",
	 "capacity": "Capacity: 7500",
	 "address1": "1300 S. Lynn White Drive",
	 "city": "Chicago",
	 "state": "IL",
	 "postal": "60605",
	 "country": "USA",
	 "phone": "(312) 540-2668",
	 "venueURL": "http://www.livenation.com/Charter-One-Pavilion-at-Northerly-Island-tickets-Chicago/venue/33036",
	 "setlistURL": "http://deadheadland.com/furthur20120717",
	 "seatingURL": "http://media.ticketmaster.com/ln/en-us/tmimages/venue/maps/ch1/13471s.gif",
	 "suppressMapsVenue": false,
	 "coordinates":"",
	 "tourName": "Summer 2012"		
	},
	{"id": 7, 
	 "date": "7/18", 
	 "dayOfWeek": "Wednesday", 
	 "monthDate": "July 18",
	 "year": "2012", 
	 "venue": "Meadow Brook Music Festival",
	 "venueNoSpecialChars": "Meadow Brook Music Festival",
	 "altName": "Rochester Hills",
	 "showTimes": "Show: 7:00pm Doors: 5:30pm CDT",
	 "capacity": "",
	 "address1": "3554 Walton Blvd",
	 "city": "Rochester Hills",
	 "state": "MI",
	 "postal": "48309",
	 "country": "USA",
	 "phone": "(248) 377-0100",
	 "venueURL": "http://www.palacenet.com/default.asp?event=2114",
	 "setlistURL": "http://deadheadland.com/furthur20120718",
	 "seatingURL": "http://www.palacenet.com/images/venues/Mbseating.gif",
	 "suppressMapsVenue": false,
	 "coordinates":"",
	 "tourName": "Summer 2012"		
	},
	{"id": 8, 
	 "date": "9/21", 
	 "dayOfWeek": "Friday", 
	 "monthDate": "September 21",
	 "year": "2012", 
	 "venue": "Red Rocks Amphitheatre",
	 "venueNoSpecialChars": "Red Rocks Amphitheatre",
	 "altName": "Red Rocks",
	 "showTimes": "Show: 7:30pm Doors: 6:00pm MDT",
	 "capacity": "Capacity: 9450",
	 "address1": "18300 West Alameda Parkway",
	 "city": "Morrison",
	 "state": "CO",
	 "postal": "80465",
	 "country": "USA",
	 "phone": "720-865-2494",
	 "venueURL": "http://www.redrocksonline.com/",
	 "setlistURL": "http://deadheadland.com/furthur20120921",
	 "seatingURL": "http://media.ticketmaster.com/tm/en-us/tmimages/venue/maps/mtn/18721s.gif",
	 "suppressMapsVenue": false,
	 "coordinates":"",
	 "tourName": "Summer 2012"		
	},
	{"id": 9, 
	 "date": "9/22", 
	 "dayOfWeek": "Saturday", 
	 "monthDate": "September 22",
	 "year": "2012", 
	 "venue": "Red Rocks Amphitheatre",
	 "venueNoSpecialChars": "Red Rocks Amphitheatre",
	 "altName": "Red Rocks",
	 "showTimes": "Show: 7:30pm Doors: 6:00pm MDT",
	 "capacity": "Capacity: 9450",
	 "address1": "18300 West Alameda Parkway",
	 "city": "Morrison",
	 "state": "CO",
	 "postal": "80465",
	 "country": "USA",
	 "phone": "720-865-2494",
	 "venueURL": "http://www.redrocksonline.com/",
	 "setlistURL": "http://deadheadland.com/furthur20120922",
	 "seatingURL": "http://media.ticketmaster.com/tm/en-us/tmimages/venue/maps/mtn/18721s.gif",
	 "suppressMapsVenue": false,
	 "coordinates":"",
	 "tourName": "Summer 2012"		
	},
	{"id": 10, 
	 "date": "9/23", 
	 "dayOfWeek": "Sunday", 
	 "monthDate": "September 23",
	 "year": "2012", 
	 "venue": "Red Rocks Amphitheatre",
	 "venueNoSpecialChars": "Red Rocks Amphitheatre",
	 "altName": "Red Rocks",
	 "showTimes": "Show: 5:00pm Doors: 3:30pm MDT",
	 "capacity": "Capacity: 9450",
	 "address1": "18300 West Alameda Parkway",
	 "city": "Morrison",
	 "state": "CO",
	 "postal": "80465",
	 "country": "USA",
	 "phone": "720-865-2494",
	 "venueURL": "http://www.redrocksonline.com/",
	 "setlistURL": "http://deadheadland.com/furthur20120923",
	 "seatingURL": "http://media.ticketmaster.com/tm/en-us/tmimages/venue/maps/mtn/18721s.gif",
	 "suppressMapsVenue": false,
	 "coordinates":"",
	 "tourName": "Summer 2012"		
	},
	{"id": 11, 
	 "date": "9/25", 
	 "dayOfWeek": "Tuesday", 
	 "monthDate": "September 25",
	 "year": "2012", 
	 "venue": "WaMu Theater",
	 "venueNoSpecialChars": "WaMu Theater",
	 "altName": "Seattle",
	 "showTimes": "Show: 7:30pm Doors: 6:00pm PDT",
	 "capacity": "Capacity: ???",
	 "address1": "800 Occidental Ave. S.",
	 "city": "Seattle",
	 "state": "WA",
	 "postal": "98134",
	 "country": "USA",
	 "phone": "(206) 381-7555",
	 "venueURL": "http://www.wamutheater.com/",
	 "setlistURL": "http://deadheadland.com/furthur20120925",
	 "seatingURL": "http://www.wamutheater.com/images/content/Seating_Orch.gif",
	 "suppressMapsVenue": false,
	 "coordinates":"",
	 "tourName": "Summer 2012"		
	},
	{"id": 12, 
	 "date": "9/27", 
	 "dayOfWeek": "Thursday", 
	 "monthDate": "September 27",
	 "year": "2012", 
	 "venue": "Edgefield",
	 "venueNoSpecialChars": "Edgefield",
	 "altName": "Edgefield",
	 "showTimes": "Show: 6:00pm Doors: 4:30pm PDT",
	 "capacity": "Capacity: 1500",
	 "address1": "2126 S.W. Halsey St.",
	 "city": "Troutdale",
	 "state": "OR",
	 "postal": "97060",
	 "country": "USA",
	 "phone": "(503) 669-8610",
	 "venueURL": "http://www.edgefieldconcerts.com/",
	 "setlistURL": "http://deadheadland.com/furthur20120927",
	 "seatingURL": "http://www.edgefieldconcerts.com/images/RSseatingchart.png",
	 "suppressMapsVenue": false,
	 "coordinates":"",
	 "tourName": "Summer 2012"		
	},
	{"id": 13, 
	 "date": "9/28", 
	 "dayOfWeek": "Friday", 
	 "monthDate": "September 28",
	 "year": "2012", 
	 "venue": "Edgefield",
	 "venueNoSpecialChars": "Edgefield",
	 "altName": "Edgefield",
	 "showTimes": "Show: 6:00pm Doors: 4:30pm PDT",
	 "capacity": "Capacity: 1500",
	 "address1": "2126 S.W. Halsey St.",
	 "city": "Troutdale",
	 "state": "OR",
	 "postal": "97060",
	 "country": "USA",
	 "phone": "(503) 669-8610",
	 "venueURL": "http://www.edgefieldconcerts.com/",
	 "setlistURL": "http://deadheadland.com/furthur20120928",
	 "seatingURL": "http://www.edgefieldconcerts.com/images/RSseatingchart.png",
	 "suppressMapsVenue": false,
	 "coordinates":"",
	 "tourName": "Summer 2012"		
	},
	{"id": 14, 
	 "date": "9/29", 
	 "dayOfWeek": "Saturday", 
	 "monthDate": "September 29",
	 "year": "2012", 
	 "venue": "Edgefield",
	 "venueNoSpecialChars": "Edgefield",
	 "altName": "Edgefield",
	 "showTimes": "Show: 6:00pm Doors: 4:30pm PDT",
	 "capacity": "Capacity: 1500",
	 "address1": "2126 S.W. Halsey St.",
	 "city": "Troutdale",
	 "state": "OR",
	 "postal": "97060",
	 "country": "USA",
	 "phone": "(503) 669-8610",
	 "venueURL": "http://www.edgefieldconcerts.com/",
	 "setlistURL": "http://deadheadland.com/furthur20120929",
	 "seatingURL": "http://www.edgefieldconcerts.com/images/RSseatingchart.png",
	 "suppressMapsVenue": false,
	 "coordinates":"",
	 "tourName": "Summer 2012"		
	},
	{"id": 15, 
	 "date": "9/30", 
	 "dayOfWeek": "Sunday", 
	 "monthDate": "September 30",
	 "year": "2012", 
	 "venue": "Shoreline Amphitheatre",
	 "venueNoSpecialChars": "Shoreline Amphitheatre",
	 "altName": "Shoreline",
	 "showTimes": "Show: 7:00pm Doors: 5:30pm PDT",
	 "capacity": "Capacity: 22,000",
	 "address1": "One Amphitheatre Parkway",
	 "city": "Mountain View",
	 "state": "CA",
	 "postal": "94043",
	 "country": "USA",
	 "phone": "(650) 967-3000",
	 "venueURL": "http://www.theshorelineamphitheatre.com/",
	 "setlistURL": "http://deadheadland.com/furthur20120930",
	 "seatingURL": "http://media.ticketmaster.com/tm/en-us/tmimages/venue/maps/nca/32890s.gif",
	 "suppressMapsVenue": false,
	 "coordinates":"",
	 "tourName": "Summer 2012"		
	},
	{"id": 16, 
	 "date": "10/2", 
	 "dayOfWeek": "Tuesday", 
	 "monthDate": "October 2",
	 "year": "2012", 
	 "venue": "SDSU Open Air Theatre",
	 "venueNoSpecialChars": "SDSU Open Air Theatre",
	 "altName": "San Diego",
	 "showTimes": "Show: 7:00pm Doors: 5:30pm PDT",
	 "capacity": "Capacity: 4600",
	 "address1": "5500 Campanile Drive",
	 "city": "San Diego",
	 "state": "CA",
	 "postal": "92182",
	 "country": "USA",
	 "phone": "(619) 594-0429",
	 "venueURL": "http://as.sdsu.edu/viejas_arena/oat.html",
	 "setlistURL": "http://deadheadland.com/furthur20121002",
	 "seatingURL": "http://www.as.sdsu.edu/viejas_arena/images_global/map_oat_sc_large.gif",
	 "suppressMapsVenue": false,
	 "coordinates":"",
	 "tourName": "Summer 2012"		
	},
	{"id": 17, 
	 "date": "10/4", 
	 "dayOfWeek": "Thursday", 
	 "monthDate": "October 4",
	 "year": "2012", 
	 "venue": "The Joint at Hard Rock",
	 "venueNoSpecialChars": "The Joint at Hard Rock",
	 "altName": "Las Vegas",
	 "showTimes": "Show: 8:00pm Doors: 6:30pm PDT",
	 "capacity": "Capacity: 4,000",
	 "address1": "4455 Paradise Road",
	 "city": "Las Vegas",
	 "state": "NV",
	 "postal": "89169",
	 "country": "USA",
	 "phone": "702-693-5583",
	 "venueURL": "http://www.thejointlasvegas.com/",
	 "setlistURL": "http://deadheadland.com/furthur20121004",
	 "seatingURL": "http://media.ticketmaster.com/tm/en-us/tmimages/venue/maps/t44/39077s.gif",
	 "suppressMapsVenue": false,
	 "coordinates":"",
	 "tourName": "Summer 2012"		
	},
	{"id": 18, 
	 "date": "10/5", 
	 "dayOfWeek": "Friday", 
	 "monthDate": "October 5",
	 "year": "2012", 
	 "venue": "Greek Theatre",
	 "venueNoSpecialChars": "Greek Theatre",
	 "altName": "Los Angeles",
	 "showTimes": "Show: 7:00pm Doors: 5:30pm PDT",
	 "capacity": "Capacity: 6,162",
	 "address1": " 2700 North Vermont Ave.",
	 "city": "Los Angeles",
	 "state": "CA",
	 "postal": "90027",
	 "country": "USA",
	 "phone": "323-665-5857",
	 "venueURL": "http://www.greektheatrela.com/",
	 "setlistURL": "http://deadheadland.com/furthur20121005",
	 "seatingURL": "http://www.greektheatrela.com/info/images/seat_reserved1.gif",
	 "suppressMapsVenue": false,
	 "coordinates":"",
	 "tourName": "Summer 2012"		
	},
	{"id": 19, 
	 "date": "10/6", 
	 "dayOfWeek": "Saturday", 
	 "monthDate": "October 6",
	 "year": "2012", 
	 "venue": "Greek Theatre",
	 "venueNoSpecialChars": "Greek Theatre",
	 "altName": "Los Angeles",
	 "showTimes": "Show: 7:00pm Doors: 5:30pm PDT",
	 "capacity": "Capacity: 6,162",
	 "address1": " 2700 North Vermont Ave.",
	 "city": "Los Angeles",
	 "state": "CA",
	 "postal": "90027",
	 "country": "USA",
	 "phone": "323-665-5857",
	 "venueURL": "http://www.greektheatrela.com/",
	 "setlistURL": "http://deadheadland.com/furthur20121006",
	 "seatingURL": "http://www.greektheatrela.com/info/images/seat_reserved1.gif",
	 "suppressMapsVenue": false,
	 "coordinates":"",
	 "tourName": "Summer 2012"		
	},
	{"id": 20, 
	 "date": "10/7", 
	 "dayOfWeek": "Sunday", 
	 "monthDate": "October 7",
	 "year": "2012", 
	 "venue": "Santa Barbara Bowl",
	 "venueNoSpecialChars": "Santa Barbara Bowl",
	 "altName": "Santa Barbara",
	 "showTimes": "Show: 6:00pm Doors: 4:30pm PDT",
	 "capacity": "Capacity: 4562",
	 "address1": "1122 N. Milpas Street",
	 "city": "Santa Barbara",
	 "state": "CA",
	 "postal": "93103",
	 "country": "USA",
	 "phone": "(805) 962-7411",
	 "venueURL": "http://www.sbbowl.com/",
	 "setlistURL": "http://deadheadland.com/furthur20121007",
	 "seatingURL": "http://www.sbbowl.com/seating.htm",
	 "suppressMapsVenue": false,
	 "coordinates":"",
	 "tourName": "Summer 2012"		
	}
]
